twitter_demographer/__init__.py
twitter_demographer/components.py
twitter_demographer/twitter_demographer.py
twitter_demographer/analyzer/__init__.py
twitter_demographer/analyzer/empath.py
twitter_demographer/analyzer/liwc.py
twitter_demographer/classification/__init__.py
twitter_demographer/classification/perspective.py
twitter_demographer/classification/transformers.py
twitter_demographer/clustering/__init__.py
twitter_demographer/clustering/clusters.py
twitter_demographer/clustering/topic_modeling.py
twitter_demographer/demographics/__init__.py
twitter_demographer/demographics/m3.py
twitter_demographer/geolocation/__init__.py
twitter_demographer/geolocation/geonames.py
twitter_demographer/geolocation/nominatim.py
twitter_demographer/support/__init__.py
twitter_demographer/support/dataset.py
twitter_demographer/support/utils.py
twitter_demographer-0.2.1.dist-info/AUTHORS.rst
twitter_demographer-0.2.1.dist-info/LICENSE
twitter_demographer-0.2.1.dist-info/METADATA
twitter_demographer-0.2.1.dist-info/WHEEL
twitter_demographer-0.2.1.dist-info/top_level.txt
twitter_demographer-0.2.1.dist-info/RECORD
