Metadata-Version: 2.1
Name: twitter-demographer
Version: 0.2.1
Summary: Twitter Demographer
Home-page: https://github.com/MilaNLProc/twitter-demographer
Author: Federico Bianchi
Author-email: f.bianchi@unibocconi.it
License: MIT license
Keywords: twitter_demographer
Platform: UNKNOWN
Classifier: Development Status :: 2 - Pre-Alpha
Classifier: Intended Audience :: Developers
Classifier: License :: OSI Approved :: MIT License
Classifier: Natural Language :: English
Classifier: Programming Language :: Python :: 3
Classifier: Programming Language :: Python :: 3.6
Classifier: Programming Language :: Python :: 3.7
Classifier: Programming Language :: Python :: 3.8
Requires-Python: >=3.6
Requires-Dist: pandas
Requires-Dist: sklearn
Requires-Dist: scipy
Requires-Dist: tqdm
Requires-Dist: tweepy
Requires-Dist: liwc (==0.5.0)
Requires-Dist: empath
Requires-Dist: transformers (>=4.19.2)
Requires-Dist: torch (==1.9.0)
Requires-Dist: m3inference (==1.1.5)
Requires-Dist: appdirs (==1.4.4)
Requires-Dist: geocoder
Requires-Dist: datasets
Requires-Dist: contextualized-topic-models
Requires-Dist: umap
Requires-Dist: hdbscan
